taskcontroller/__init__.py
taskcontroller/cli.py
taskcontroller/flow_control_decorator.py
taskcontroller/shared_var.py
taskcontroller-0.2.0.dist-info/licenses/LICENSE
taskcontroller-0.2.0.dist-info/METADATA
taskcontroller-0.2.0.dist-info/WHEEL
taskcontroller-0.2.0.dist-info/entry_points.txt
taskcontroller-0.2.0.dist-info/top_level.txt
taskcontroller-0.2.0.dist-info/RECORD
