Metadata-Version: 2.4
Name: taskController
Version: 0.2.0
Summary: A Python library for pause/resume/kill control of functions across processes
Home-page: https://github.com/yuvimehta/taskController
Author: Orangewood Labs
Author-email: Yuvraj.m@orangewood.co
Project-URL: Bug Reports, https://github.com/yuvimehta/taskController/issues
Project-URL: Source, https://github.com/yuvimehta/taskController
Keywords: flow-control pause resume kill decorator process-control
Classifier: Development Status :: 3 - Alpha
Classifier: Intended Audience :: Developers
Classifier: Topic :: Software Development :: Libraries :: Python Modules
Classifier: Programming Language :: Python :: 3
Classifier: Programming Language :: Python :: 3.7
Classifier: Programming Language :: Python :: 3.8
Classifier: Programming Language :: Python :: 3.9
Classifier: Programming Language :: Python :: 3.10
Classifier: Programming Language :: Python :: 3.11
Classifier: License :: OSI Approved :: MIT License
Classifier: Operating System :: OS Independent
Requires-Python: >=3.7
License-File: LICENSE
Requires-Dist: dill>=0.3.0
Dynamic: author
Dynamic: author-email
Dynamic: classifier
Dynamic: description
Dynamic: description-content-type
Dynamic: home-page
Dynamic: keywords
Dynamic: license-file
Dynamic: project-url
Dynamic: requires-dist
Dynamic: requires-python
Dynamic: summary
